setup.py
src/bael/__init__.py
src/bael/hatak/__init__.py
src/bael/hatak/alembic.py
src/bael/hatak/recipe.py
src/bael/hatak/tasks.py
src/bael/hatak/templates.py
src/bael/hatak/uwsgi.py
src/bael/hatak/templates/frontend.ini.tpl
src/bael/hatak/templates/project/conftest.py.tpl
src/bael/hatak/templates/project/fixtures.py.tpl
src/bael/hatak/templates/project/init.py.tpl
src/bael/hatak/templates/project/manage.py.tpl
src/bael/hatak/templates/project/pytest.ini.tpl
src/bael/hatak/templates/project/readme.txt.tpl
src/bael/hatak/templates/project/routes.py.tpl
src/bael/hatak/templates/project/settings.py.tpl
src/bael/hatak/templates/project/testsettings.py.tpl
src/hatak/__init__.py
src/hatak/application.py
src/hatak/command.py
src/hatak/controller.py
src/hatak/errors.py
src/hatak/plugin.py
src/hatak/route.py
src/hatak/testing.py
src/hatak/unpackrequest.py
src/hatak.egg-info/PKG-INFO
src/hatak.egg-info/SOURCES.txt
src/hatak.egg-info/dependency_links.txt
src/hatak.egg-info/entry_points.txt
src/hatak.egg-info/namespace_packages.txt
src/hatak.egg-info/not-zip-safe
src/hatak.egg-info/requires.txt
src/hatak.egg-info/top_level.txt