Metadata-Version: 1.0
Name: hatak
Version: 0.2.7.9
Summary: Small Pyramid extension/project managment
Home-page: https://github.com/socek/hatak
Author: UNKNOWN
Author-email: UNKNOWN
License: Apache License 2.0
Platform: UNKNOWN
